LICENSE
MANIFEST.in
README.md
requirements.txt
setup.py
k_means_plus_plus/__init__.py
k_means_plus_plus/_version.py
k_means_plus_plus/cluster.py
k_means_plus_plus.egg-info/PKG-INFO
k_means_plus_plus.egg-info/SOURCES.txt
k_means_plus_plus.egg-info/dependency_links.txt
k_means_plus_plus.egg-info/requires.txt
k_means_plus_plus.egg-info/top_level.txt