Metadata-Version: 1.0
Name: k-means-plus-plus
Version: 0.1.0
Summary: K-Means++ Clustering for Pandas DataFrames
Home-page: https://github.com/jackmaney/k-means-plus-plus-pandas
Author: Jack Maney
Author-email: jackmaney@gmail.com
License: MIT
Platform: UNKNOWN
